mlagility/__init__.py
mlagility/parser.py
mlagility/version.py
onnxflow/__init__.py
onnxflow/version.py
mlagility-2.1.2.dist-info/LICENSE
mlagility-2.1.2.dist-info/METADATA
mlagility-2.1.2.dist-info/WHEEL
mlagility-2.1.2.dist-info/entry_points.txt
mlagility-2.1.2.dist-info/top_level.txt
mlagility-2.1.2.dist-info/RECORD
