Metadata-Version: 2.1
Name: mlagility
Version: 2.1.2
Summary: MLAgility Benchmark and Tools
Home-page: https://github.com/groq/mlagility
Author: Jeremy Fowers, Daniel Holanda, Ramakrishnan Sivakumar, Victoria Godsoe
Author-email: jfowers@groq.com, dhnoronha@groq.com, rsivakumar@groq.com, vgodsoe@groq.com
License: MIT
Requires-Python: >=3.8, <3.11
License-File: LICENSE
Requires-Dist: invoke (>=2.0.0)
Requires-Dist: onnx (>=1.11.0)
Requires-Dist: onnxmltools (==1.10.0)
Requires-Dist: hummingbird-ml (==0.4.4)
Requires-Dist: scikit-learn (==1.1.1)
Requires-Dist: xgboost (==1.6.1)
Requires-Dist: onnxruntime (>=1.10.0)
Requires-Dist: paramiko (==2.11.0)
Requires-Dist: torch (>=1.12.1)
Requires-Dist: protobuf (>=3.17.3)
Requires-Dist: pyyaml (>=5.4)
Requires-Dist: typeguard (>=2.3.13)
Requires-Dist: packaging (>=21.3)
Provides-Extra: groq
Requires-Dist: groqflow (==2.5.2) ; extra == 'groq'
Provides-Extra: tensorflow
Requires-Dist: tensorflow-cpu (<2.12,>=2.8.1) ; extra == 'tensorflow'
Requires-Dist: tf2onnx (>=1.12.0) ; extra == 'tensorflow'
